remote_sensing_processor/__init__.py
remote_sensing_processor/common/__init__.py
remote_sensing_processor/common/common_functions.py
remote_sensing_processor/common/dask.py
remote_sensing_processor/common/normalize.py
remote_sensing_processor/common/rasterize.py
remote_sensing_processor/common/replace.py
remote_sensing_processor/common/torch_test.py
remote_sensing_processor/imagery_types/__init__.py
remote_sensing_processor/imagery_types/types.py
remote_sensing_processor/indices/__init__.py
remote_sensing_processor/indices/normalized_difference.py
remote_sensing_processor/landsat/__init__.py
remote_sensing_processor/landsat/landsat.py
remote_sensing_processor/mosaic/__init__.py
remote_sensing_processor/mosaic/mosaic.py
remote_sensing_processor/segmentation/__init__.py
remote_sensing_processor/segmentation/mapping.py
remote_sensing_processor/segmentation/models.py
remote_sensing_processor/segmentation/segmentation.py
remote_sensing_processor/segmentation/tiles.py
remote_sensing_processor/sentinel2/__init__.py
remote_sensing_processor/sentinel2/sen2cor/__init__.py
remote_sensing_processor/sentinel2/sen2cor/sen2cor.py
remote_sensing_processor/sentinel2/sentinel_postprocessing/__init__.py
remote_sensing_processor/sentinel2/sentinel_postprocessing/sentinel_postprocessing.py
remote_sensing_processor/sentinel2/superres/DSen2Net.py
remote_sensing_processor/sentinel2/superres/__init__.py
remote_sensing_processor/sentinel2/superres/patches.py
remote_sensing_processor/sentinel2/superres/superres.py
remote_sensing_processor/sentinel2/superres/supres.py
remote_sensing_processor/sentinel2/superres/weights/L1C20M.pt
remote_sensing_processor/sentinel2/superres/weights/L1C60M.pt
remote_sensing_processor/sentinel2/superres/weights/L2A20M.pt
remote_sensing_processor/sentinel2/superres/weights/L2A60M.pt
remote_sensing_processor/sentinel2/superres/weights/__init__.py
remote_sensing_processor/unzip/__init__.py
remote_sensing_processor/unzip/unzip.py
remote_sensing_processor-0.2.2.dist-info/LICENSE
remote_sensing_processor-0.2.2.dist-info/METADATA
remote_sensing_processor-0.2.2.dist-info/WHEEL
remote_sensing_processor-0.2.2.dist-info/top_level.txt
remote_sensing_processor-0.2.2.dist-info/RECORD
