Metadata-Version: 2.1
Name: remote-sensing-processor
Version: 0.2.2
Summary: RSP is a tool for geospatial raster data processing
Home-page: https://github.com/simonreise/remote-sensing-processor
Author: Mikhail Moskovchenko
Author-email: moskovchenkomike@gmail.com
Project-URL: Bug Tracker, https://github.com/simonreise/remote-sensing-processor/issues
Project-URL: Source, https://github.com/simonreise/remote-sensing-processor
Project-URL: Documentation, https://remote-sensing-processor.readthedocs.io
Keywords: remote sensing,landsat,sentinel,gdal,rasterio
Classifier: Programming Language :: Python :: 3
Classifier: License :: OSI Approved :: GNU General Public License v3 (GPLv3)
Classifier: Operating System :: OS Independent
Classifier: Environment :: GPU :: NVIDIA CUDA
Classifier: Topic :: Scientific/Engineering :: GIS
Requires-Python: >=3.8
License-File: LICENSE
Requires-Dist: numpy >=1.17
Requires-Dist: dask
Requires-Dist: torch >=2.0
Requires-Dist: torchvision >=0.10
Requires-Dist: lightning
Requires-Dist: tensorboard
Requires-Dist: transformers
Requires-Dist: timm
Requires-Dist: xgboost
Requires-Dist: scikit-learn
Requires-Dist: scikit-image
Requires-Dist: rasterio >=1.2
Requires-Dist: rioxarray
Requires-Dist: pyproj
Requires-Dist: geopandas
Requires-Dist: geocube
Requires-Dist: zarr
